README.md
setup.cfg
setup.py
dl202111.egg-info/PKG-INFO
dl202111.egg-info/SOURCES.txt
dl202111.egg-info/dependency_links.txt
dl202111.egg-info/top_level.txt
helloapp/__init__.py
helloapp/hello.py
myapp/__init__.py
myapp/myapplication.py